zerocap_api/__init__.py
zerocap_api/main.py
zerocap_api-0.1.15.dist-info/METADATA
zerocap_api-0.1.15.dist-info/WHEEL
zerocap_api-0.1.15.dist-info/top_level.txt
zerocap_api-0.1.15.dist-info/RECORD
