Metadata-Version: 2.1
Name: zerocap-api
Version: 0.1.15
Summary: zerocap_api
Home-page: https://zerocap.com/
Author: zerocap
Author-email: jiayu.gao@eigen.capital
License: MIT
Platform: all
Classifier: Programming Language :: Python :: 3
Classifier: License :: OSI Approved :: MIT License
Classifier: Operating System :: OS Independent
Requires-Python: >=3.6
Requires-Dist: requests
Requires-Dist: websockets (>=11.0.3)
